{
  "name": "v6-session-basics",
  "code_url": "https://github.com/vantage6/v6-session-basics",
  "description": "This algorithm demonstrates the basics of a session.",
  "reviews": [],
  "vantage6_version": "4.9",
  "partitioning": "horizontal",
  "functions": [
    {
      "name": "global_sum",
      "display_name": "Sum",
      "standalone": true,
      "description": "Compute the global sum of a federated dataset",
      "ui_visualizations": [],
      "step_type": "central_compute",
      "arguments": [
        {
          "has_default_value": false,
          "conditional_value": null,
          "name": "column",
          "display_name": "Column to sum",
          "conditional_operator": null,
          "description": "Computes the global sum of the given column",
          "type": "column",
          "default_value": "",
          "is_frontend_only": false
        }
      ],
      "databases": [
        {
          "name": "database",
          "description": ""
        }
      ]
    },
    {
      "name": "sleep",
      "display_name": "Sleep",
      "standalone": true,
      "description": "Sleep for a given number of seconds",
      "ui_visualizations": [],
      "step_type": "federated_compute",
      "arguments": [
        {
          "type": "integer",
          "conditional_operator": null,
          "description": "Amount of time that the function should sleep",
          "name": "seconds",
          "has_default_value": false,
          "conditional_value": null,
          "is_frontend_only": false,
          "display_name": "Seconds",
          "default_value": ""
        }
      ],
      "databases": []
    },
    {
      "name": "read_csv",
      "display_name": "Read CSV file",
      "standalone": true,
      "description": "",
      "ui_visualizations": [],
      "step_type": "data_extraction",
      "arguments": [],
      "databases": [
        {
          "description": "",
          "name": "Database"
        }
      ]
    },
    {
      "name": "pre_process",
      "display_name": "Change column dtype",
      "standalone": true,
      "description": "Change data type of particular column (e.g. string to int)",
      "ui_visualizations": [],
      "step_type": "preprocessing",
      "arguments": [
        {
          "has_default_value": false,
          "conditional_value": null,
          "name": "column",
          "display_name": "Column ",
          "conditional_operator": null,
          "description": "Column to change data type of ",
          "type": "column",
          "default_value": "",
          "is_frontend_only": false
        },
        {
          "has_default_value": false,
          "conditional_value": null,
          "name": "dtype",
          "display_name": "New data type",
          "conditional_operator": null,
          "description": "",
          "type": "string",
          "default_value": "",
          "is_frontend_only": false
        }
      ],
      "databases": []
    },
    {
      "name": "sum",
      "display_name": "Sum",
      "standalone": true,
      "description": "",
      "ui_visualizations": [],
      "step_type": "federated_compute",
      "arguments": [
        {
          "has_default_value": false,
          "conditional_value": null,
          "name": "column",
          "display_name": "Column to sum",
          "conditional_operator": null,
          "description": "",
          "type": "column",
          "default_value": "",
          "is_frontend_only": false
        }
      ],
      "databases": [
        {
          "name": "database",
          "description": ""
        }
      ]
    }
  ],
  "documentation_url": "",
  "image": "harbor2.vantage6.ai/algorithms/session-basics"
}
